philly/__init__.py
philly/__main__.py
philly/loaders.py
philly/philly.py
philly/datasets/2009-2012_Police_Advisory_Commission_Complaints.yaml
philly/datasets/2015_Parking_Meter___Kiosk_Inventory.yaml
philly/datasets/2020_Census_to_Police_District_Crosswalk.yaml
philly/datasets/311_Service_and_Information_Requests.yaml
philly/datasets/AMS_Latest_Air_Quality_Sensor_Readings.yaml
philly/datasets/ARCHIVED__2007-2015_Litter_Index.yaml
philly/datasets/ARCHIVED__Greenworks_Metrics.yaml
philly/datasets/ARCHIVED__Healthy_Chinese_Takeout.yaml
philly/datasets/ARCHIVED__Philadelphia_Food_Access.yaml
philly/datasets/ARCHIVED__Valet_Parking_Locations.yaml
philly/datasets/Active_Residential_Parking_Permits_by_District.yaml
philly/datasets/Advancing_Education_Safely.yaml
philly/datasets/Aerial_Photography__imagery_.yaml
philly/datasets/Affordable_Housing_Production.yaml
philly/datasets/Air_Monitoring_Stations.yaml
philly/datasets/Air_Quality_Index_Days.yaml
philly/datasets/Arterial_Streets.yaml
philly/datasets/Big_Belly_Trash_Bin_Usage.yaml
philly/datasets/Big_Belly_Waste_Baskets__Trash_Bins_.yaml
philly/datasets/Bike_Network.yaml
philly/datasets/Bike_Network_-_Supporting_Datasets.yaml
philly/datasets/Boost_Your_Business_Program.yaml
philly/datasets/Bridge_Locations.yaml
philly/datasets/Building_Demolitions.yaml
philly/datasets/Building_Footprints.yaml
philly/datasets/Bullet_Voting_2015.yaml
philly/datasets/Bus_Shelters.yaml
philly/datasets/Business_Improvement_Districts__BID_.yaml
philly/datasets/Business_Technical_Support_Resources.yaml
philly/datasets/Buy_Fresh__Buy_Local_PA.yaml
philly/datasets/COVID-19_Test_Sites.yaml
philly/datasets/COVID-19_Vaccinations.yaml
philly/datasets/COVID_Cumulative_Historical_Snapshots.yaml
philly/datasets/COVID_Deaths.yaml
philly/datasets/COVID_Hospitalizations.yaml
philly/datasets/COVID_Tests_and_Cases.yaml
philly/datasets/Campaign_Finance_Reports.yaml
philly/datasets/Candidates.yaml
philly/datasets/Candidates_for_Elected_Office.yaml
philly-0.1.0.dist-info/licenses/LICENSE
philly-0.1.0.dist-info/METADATA
philly-0.1.0.dist-info/WHEEL
philly-0.1.0.dist-info/entry_points.txt
philly-0.1.0.dist-info/top_level.txt
philly-0.1.0.dist-info/RECORD
