Metadata-Version: 2.4
Name: philly
Version: 0.1.0
Requires-Python: >=3.10
License-File: LICENSE
Requires-Dist: fire[cli]>=0.7.0
Requires-Dist: geojson>=3.2.0
Requires-Dist: geoparquet>=0.0.3
Requires-Dist: gtfs-realtime-bindings>=1.0.0
Requires-Dist: geopandas>=1.1.0
Requires-Dist: httpx>=0.28.1
Requires-Dist: pandas>=2.3.0
Requires-Dist: pydantic>=2.11.3
Requires-Dist: pyyaml>=6.0.2
Requires-Dist: tqdm>=4.67.1
Dynamic: license-file
